task1/lfsr.sv
module lfsr(
    input logic clk,
    input logic rst,
    input logic en,
    input logic [4:1] data_in ,
    output logic [4:1] data_out 
);

    logic [4:1] sreg;
   // assign sreg = data_in;
    always_ff @(posedge clk) begin
        if (rst)
            sreg <= data_in;
        else if (en) begin
            sreg[4] <= sreg[3];
            sreg[3] <= sreg[2];
            sreg[2] <= sreg[1];
            sreg[1] <= sreg[3] ^ sreg[4];
        end
    end
    assign data_out = {sreg[4],sreg[3],sreg[2],sreg[1]};
endmodule

task1/counter.vcd
$version Generated by VerilatedVcd $end
$date Fri Nov  4 05:53:23 2022 $end
$timescale 1ps $end

 $scope module TOP $end
  $var wire  1 # clk $end
  $var wire  4 & data_in [4:1] $end
  $var wire  4 ' data_out [4:1] $end
  $var wire  1 % en $end
  $var wire  1 $ rst $end
  $scope module lfsr $end
   $var wire  1 # clk $end
   $var wire  4 & data_in [4:1] $end
   $var wire  4 ' data_out [4:1] $end
   $var wire  1 % en $end
   $var wire  1 $ rst $end
   $var wire  4 ( sreg [4:1] $end
  $upscope $end
 $upscope $end
$enddefinitions $end


#0
1#
1$
0%
b0000 &
b0000 '
b0000 (
#1
0#
#2
1#
b0001 &
#3
0#
#4
1#
b0001 '
b0001 (
#5
0#
#6
1#
#7
0#
#8
1#
#9
0#
#10
1#
#11
0#
#12
1#
0$
#13
0#
#14
1#
#15
0#
#16
1#
#17
0#
#18
1#
#19
0#
#20
1#
#21
0#
#22
1#
#23
0#
#24
1#
#25
0#
#26
1#
#27
0#
#28
1#
#29
0#
#30
1#
#31
0#
#32
1#
#33
0#
#34
1#
#35
0#
#36
1#
#37
0#
#38
1#
#39
0#
#40
1#
#41
0#
#42
1#
#43
0#
#44
1#
#45
0#
#46
1#
#47
0#
#48
1#
#49
0#
#50
1#
#51
0#
#52
1#
#53
0#
#54
1#
#55
0#
#56
1#
#57
0#
#58
1#
#59
0#
#60
1#
#61
0#
#62
1#
#63
0#
#64
1#
#65
0#
#66
1#
#67
0#
#68
1#
#69
0#
#70
1#
#71
0#
#72
1#
#73
0#
#74
1#
#75
0#
#76
1#
#77
0#
#78
1#
#79
0#
#80
1#
#81
0#
#82
1#
#83
0#
#84
1#
#85
0#
#86
1#
#87
0#
#88
1#
#89
0#
#90
1#
#91
0#
#92
1#
#93
0#
#94
1#
#95
0#
#96
1#
#97
0#
#98
1#
#99
0#
#100
1#
#101
0#
#102
1#
#103
0#
#104
1#
#105
0#
#106
1#
#107
0#
#108
1#
#109
0#
#110
1#
#111
0#
#112
1#
#113
0#
#114
1#
#115
0#
#116
1#
#117
0#
#118
1#
#119
0#
#120
1#
#121
0#
#122
1#
#123
0#
#124
1#
#125
0#
#126
1#
#127
0#
#128
1#
#129
0#
#130
1#
1%
#131
0#
#132
1#
0%
b0010 '
b0010 (
#133
0#
#134
1#
#135
0#
#136
1#
#137
0#
#138
1#
#139
0#
#140
1#
#141
0#
#142
1#
#143
0#
#144
1#
#145
0#
#146
1#
#147
0#
#148
1#
#149
0#
#150
1#
#151
0#
#152
1#
#153
0#
#154
1#
#155
0#
#156
1#
#157
0#
#158
1#
1%
#159
0#
#160
1#
0%
b0100 '
b0100 (
#161
0#
#162
1#
#163
0#
#164
1#
#165
0#
#166
1#
#167
0#
#168
1#
#169
0#
#170
1#
#171
0#
#172
1#
#173
0#
#174
1#
1%
#175
0#
#176
1#
0%
b1001 '
b1001 (
#177
0#
#178
1#
#179
0#
#180
1#
#181
0#
#182
1#
#183
0#
#184
1#
#185
0#
#186
1#
#187
0#
#188
1#
#189
0#
#190
1#
#191
0#
#192
1#
#193
0#
#194
1#
1%
#195
0#
#196
1#
b0011 '
b0011 (
#197
0#
#198
1#
0%
b0110 '
b0110 (
#199
0#
#200
1#
1%
#201
0#
#202
1#
b1101 '
b1101 (
#203
0#
#204
1#
b1010 '
b1010 (
#205
0#
#206
1#
b0101 '
b0101 (
#207
0#
#208
1#
0%
b1011 '
b1011 (
