task3/f1_fsm.sv
module f1_fsm(
    input logic clk,
    input logic rst,
    input logic en,
    output logic [8:1] data_out
);

    typedef enum { S0,S1,S2,S3,S4,S5,S6,S7,S8 } my_state;
    my_state current_state, next_state;

    always_ff @(posedge clk) begin
        if (rst) current_state <= S0;
        else if (en)  current_state <=next_state;
    end

    always_comb
        case(current_state)
            S0: next_state = S1; 
            S1: next_state = S2; 
            S2: next_state = S3; 
            S3: next_state = S4; 
            S4: next_state = S5; 
            S5: next_state = S6;
            S6: next_state = S7;
            S7: next_state = S8;
            S8: next_state = S0;
            default: next_state = S0;
        endcase
    always_comb
        case(current_state)
            S0: data_out={8'b0};
            S1: data_out={8'b1};
            S2: data_out={8'b11};
            S3: data_out={8'b111};
            S4: data_out={8'b1111};
            S5: data_out={8'b11111};
            S6: data_out={8'b111111};
            S7: data_out={8'b1111111};
            S8: data_out={8'b11111111};
            default: data_out = {8'b0};
        endcase
endmodule
    //

task2/f1_fsm.vcd
$version Generated by VerilatedVcd $end
$date Thu Nov  3 18:31:53 2022 $end
$timescale 1ps $end

 $scope module TOP $end
  $var wire  1 # clk $end
  $var wire  8 & data_out [8:1] $end
  $var wire  1 % en $end
  $var wire  1 $ rst $end
  $scope module f1_fsm $end
   $var wire  1 # clk $end
   $var wire 32 ' current_state [31:0] $end
   $var wire  8 & data_out [8:1] $end
   $var wire  1 % en $end
   $var wire 32 ( next_state [31:0] $end
   $var wire  1 $ rst $end
  $upscope $end
 $upscope $end
$enddefinitions $end


#0
1#
1$
0%
b00000000 &
b00000000000000000000000000000000 '
b00000000000000000000000000000001 (
#1
0#
#2
1#
1%
#3
0#
#4
1#
#5
0#
#6
1#
0$
#7
0#
#8
1#
b00000001 &
b00000000000000000000000000000001 '
b00000000000000000000000000000010 (
#9
0#
#10
1#
b00000011 &
b00000000000000000000000000000010 '
b00000000000000000000000000000011 (
#11
0#
#12
1#
b00000111 &
b00000000000000000000000000000011 '
b00000000000000000000000000000100 (
#13
0#
#14
1#
b00001111 &
b00000000000000000000000000000100 '
b00000000000000000000000000000101 (
#15
0#
#16
1#
b00011111 &
b00000000000000000000000000000101 '
b00000000000000000000000000000110 (
#17
0#
#18
1#
b00111111 &
b00000000000000000000000000000110 '
b00000000000000000000000000000111 (
#19
0#
#20
1#
b01111111 &
b00000000000000000000000000000111 '
b00000000000000000000000000001000 (
#21
0#
#22
1#
b11111111 &
b00000000000000000000000000001000 '
b00000000000000000000000000000000 (
#23
0#
#24
1#
b00000000 &
b00000000000000000000000000000000 '
b00000000000000000000000000000001 (
#25
0#
#26
1#
b00000001 &
b00000000000000000000000000000001 '
b00000000000000000000000000000010 (
#27
0#
#28
1#
b00000011 &
b00000000000000000000000000000010 '
b00000000000000000000000000000011 (
#29
0#
#30
1#
b00000111 &
b00000000000000000000000000000011 '
b00000000000000000000000000000100 (
#31
0#
#32
1#
b00001111 &
b00000000000000000000000000000100 '
b00000000000000000000000000000101 (
#33
0#
#34
1#
b00011111 &
b00000000000000000000000000000101 '
b00000000000000000000000000000110 (
#35
0#
#36
1#
b00111111 &
b00000000000000000000000000000110 '
b00000000000000000000000000000111 (
#37
0#
#38
1#
b01111111 &
b00000000000000000000000000000111 '
b00000000000000000000000000001000 (
#39
0#
#40
1#
b11111111 &
b00000000000000000000000000001000 '
b00000000000000000000000000000000 (
#41
0#
#42
1#
b00000000 &
b00000000000000000000000000000000 '
b00000000000000000000000000000001 (
#43
0#
#44
1#
b00000001 &
b00000000000000000000000000000001 '
b00000000000000000000000000000010 (
#45
0#
#46
1#
b00000011 &
b00000000000000000000000000000010 '
b00000000000000000000000000000011 (
#47
0#
#48
1#
b00000111 &
b00000000000000000000000000000011 '
b00000000000000000000000000000100 (
#49
0#
#50
1#
b00001111 &
b00000000000000000000000000000100 '
b00000000000000000000000000000101 (
#51
0#
#52
1#
b00011111 &
b00000000000000000000000000000101 '
b00000000000000000000000000000110 (
#53
0#
#54
1#
b00111111 &
b00000000000000000000000000000110 '
b00000000000000000000000000000111 (
#55
0#
#56
1#
b01111111 &
b00000000000000000000000000000111 '
b00000000000000000000000000001000 (
#57
0#
#58
1#
b11111111 &
b00000000000000000000000000001000 '
b00000000000000000000000000000000 (
#59
0#
#60
1#
b00000000 &
b00000000000000000000000000000000 '
b00000000000000000000000000000001 (
#61
0#
#62
1#
b00000001 &
b00000000000000000000000000000001 '
b00000000000000000000000000000010 (
#63
0#
#64
1#
b00000011 &
b00000000000000000000000000000010 '
b00000000000000000000000000000011 (
#65
0#
#66
1#
b00000111 &
b00000000000000000000000000000011 '
b00000000000000000000000000000100 (
#67
0#
#68
1#
b00001111 &
b00000000000000000000000000000100 '
b00000000000000000000000000000101 (
#69
0#
#70
1#
b00011111 &
b00000000000000000000000000000101 '
b00000000000000000000000000000110 (
#71
0#
#72
1#
b00111111 &
b00000000000000000000000000000110 '
b00000000000000000000000000000111 (
#73
0#
#74
1#
b01111111 &
b00000000000000000000000000000111 '
b00000000000000000000000000001000 (
#75
0#
#76
1#
b11111111 &
b00000000000000000000000000001000 '
b00000000000000000000000000000000 (
#77
0#
#78
1#
b00000000 &
b00000000000000000000000000000000 '
b00000000000000000000000000000001 (
#79
0#
#80
1#
b00000001 &
b00000000000000000000000000000001 '
b00000000000000000000000000000010 (
#81
0#
#82
1#
b00000011 &
b00000000000000000000000000000010 '
b00000000000000000000000000000011 (
#83
0#
#84
1#
b00000111 &
b00000000000000000000000000000011 '
b00000000000000000000000000000100 (
#85
0#
#86
1#
b00001111 &
b00000000000000000000000000000100 '
b00000000000000000000000000000101 (
#87
0#
#88
1#
b00011111 &
b00000000000000000000000000000101 '
b00000000000000000000000000000110 (
#89
0#
#90
1#
b00111111 &
b00000000000000000000000000000110 '
b00000000000000000000000000000111 (
#91
0#
#92
1#
b01111111 &
b00000000000000000000000000000111 '
b00000000000000000000000000001000 (
#93
0#
#94
1#
b11111111 &
b00000000000000000000000000001000 '
b00000000000000000000000000000000 (
#95
0#
#96
1#
b00000000 &
b00000000000000000000000000000000 '
b00000000000000000000000000000001 (
#97
0#
#98
1#
b00000001 &
b00000000000000000000000000000001 '
b00000000000000000000000000000010 (
#99
0#
#100
1#
b00000011 &
b00000000000000000000000000000010 '
b00000000000000000000000000000011 (
#101
0#
#102
1#
b00000111 &
b00000000000000000000000000000011 '
b00000000000000000000000000000100 (
#103
0#
#104
1#
b00001111 &
b00000000000000000000000000000100 '
b00000000000000000000000000000101 (
#105
0#
#106
1#
b00011111 &
b00000000000000000000000000000101 '
b00000000000000000000000000000110 (
#107
0#
#108
1#
b00111111 &
b00000000000000000000000000000110 '
b00000000000000000000000000000111 (
#109
0#
#110
1#
b01111111 &
b00000000000000000000000000000111 '
b00000000000000000000000000001000 (
#111
0#
#112
1#
b11111111 &
b00000000000000000000000000001000 '
b00000000000000000000000000000000 (
#113
0#
#114
1#
b00000000 &
b00000000000000000000000000000000 '
b00000000000000000000000000000001 (
#115
0#
#116
1#
b00000001 &
b00000000000000000000000000000001 '
b00000000000000000000000000000010 (
#117
0#
#118
1#
b00000011 &
b00000000000000000000000000000010 '
b00000000000000000000000000000011 (
#119
0#
#120
1#
b00000111 &
b00000000000000000000000000000011 '
b00000000000000000000000000000100 (
#121
0#
#122
1#
b00001111 &
b00000000000000000000000000000100 '
b00000000000000000000000000000101 (
#123
0#
#124
1#
b00011111 &
b00000000000000000000000000000101 '
b00000000000000000000000000000110 (
#125
0#
#126
1#
b00111111 &
b00000000000000000000000000000110 '
b00000000000000000000000000000111 (
#127
0#
#128
1#
b01111111 &
b00000000000000000000000000000111 '
b00000000000000000000000000001000 (
#129
0#
#130
1#
b11111111 &
b00000000000000000000000000001000 '
b00000000000000000000000000000000 (
#131
0#
#132
1#
b00000000 &
b00000000000000000000000000000000 '
b00000000000000000000000000000001 (
#133
0#
#134
1#
b00000001 &
b00000000000000000000000000000001 '
b00000000000000000000000000000010 (
#135
0#
#136
1#
b00000011 &
b00000000000000000000000000000010 '
b00000000000000000000000000000011 (
#137
0#
#138
1#
b00000111 &
b00000000000000000000000000000011 '
b00000000000000000000000000000100 (
#139
0#
#140
1#
b00001111 &
b00000000000000000000000000000100 '
b00000000000000000000000000000101 (
#141
0#
#142
1#
b00011111 &
b00000000000000000000000000000101 '
b00000000000000000000000000000110 (
#143
0#
#144
1#
b00111111 &
b00000000000000000000000000000110 '
b00000000000000000000000000000111 (
#145
0#
#146
1#
b01111111 &
b00000000000000000000000000000111 '
b00000000000000000000000000001000 (
#147
0#
#148
1#
b11111111 &
b00000000000000000000000000001000 '
b00000000000000000000000000000000 (
#149
0#
#150
1#
b00000000 &
b00000000000000000000000000000000 '
b00000000000000000000000000000001 (
#151
0#
#152
1#
b00000001 &
b00000000000000000000000000000001 '
b00000000000000000000000000000010 (
#153
0#
#154
1#
b00000011 &
b00000000000000000000000000000010 '
b00000000000000000000000000000011 (
#155
0#
#156
1#
b00000111 &
b00000000000000000000000000000011 '
b00000000000000000000000000000100 (
#157
0#
#158
1#
b00001111 &
b00000000000000000000000000000100 '
b00000000000000000000000000000101 (
#159
0#
#160
1#
b00011111 &
b00000000000000000000000000000101 '
b00000000000000000000000000000110 (
#161
0#
#162
1#
b00111111 &
b00000000000000000000000000000110 '
b00000000000000000000000000000111 (
#163
0#
#164
1#
b01111111 &
b00000000000000000000000000000111 '
b00000000000000000000000000001000 (
#165
0#
#166
1#
b11111111 &
b00000000000000000000000000001000 '
b00000000000000000000000000000000 (
#167
0#
#168
1#
b00000000 &
b00000000000000000000000000000000 '
b00000000000000000000000000000001 (
#169
0#
#170
1#
b00000001 &
b00000000000000000000000000000001 '
b00000000000000000000000000000010 (
#171
0#
#172
1#
b00000011 &
b00000000000000000000000000000010 '
b00000000000000000000000000000011 (
#173
0#
#174
1#
b00000111 &
b00000000000000000000000000000011 '
b00000000000000000000000000000100 (
#175
0#
#176
1#
b00001111 &
b00000000000000000000000000000100 '
b00000000000000000000000000000101 (
#177
0#
#178
1#
b00011111 &
b00000000000000000000000000000101 '
b00000000000000000000000000000110 (
#179
0#
#180
1#
b00111111 &
b00000000000000000000000000000110 '
b00000000000000000000000000000111 (
#181
0#
#182
1#
b01111111 &
b00000000000000000000000000000111 '
b00000000000000000000000000001000 (
#183
0#
#184
1#
b11111111 &
b00000000000000000000000000001000 '
b00000000000000000000000000000000 (
#185
0#
#186
1#
b00000000 &
b00000000000000000000000000000000 '
b00000000000000000000000000000001 (
#187
0#
#188
1#
b00000001 &
b00000000000000000000000000000001 '
b00000000000000000000000000000010 (
#189
0#
#190
1#
b00000011 &
b00000000000000000000000000000010 '
b00000000000000000000000000000011 (
#191
0#
#192
1#
b00000111 &
b00000000000000000000000000000011 '
b00000000000000000000000000000100 (
#193
0#
#194
1#
b00001111 &
b00000000000000000000000000000100 '
b00000000000000000000000000000101 (
#195
0#
#196
1#
b00011111 &
b00000000000000000000000000000101 '
b00000000000000000000000000000110 (
#197
0#
#198
1#
b00111111 &
b00000000000000000000000000000110 '
b00000000000000000000000000000111 (
#199
0#
#200
1#
b01111111 &
b00000000000000000000000000000111 '
b00000000000000000000000000001000 (
#201
0#
#202
1#
b11111111 &
b00000000000000000000000000001000 '
b00000000000000000000000000000000 (
#203
0#
#204
1#
b00000000 &
b00000000000000000000000000000000 '
b00000000000000000000000000000001 (
#205
0#
#206
1#
b00000001 &
b00000000000000000000000000000001 '
b00000000000000000000000000000010 (
#207
0#
#208
1#
b00000011 &
b00000000000000000000000000000010 '
b00000000000000000000000000000011 (
#209
0#
#210
1#
b00000111 &
b00000000000000000000000000000011 '
b00000000000000000000000000000100 (
#211
0#
#212
1#
b00001111 &
b00000000000000000000000000000100 '
b00000000000000000000000000000101 (
#213
0#
#214
1#
b00011111 &
b00000000000000000000000000000101 '
b00000000000000000000000000000110 (
#215
0#
#216
1#
b00111111 &
b00000000000000000000000000000110 '
b00000000000000000000000000000111 (
#217
0#
#218
1#
b01111111 &
b00000000000000000000000000000111 '
b00000000000000000000000000001000 (
#219
0#
#220
1#
b11111111 &
b00000000000000000000000000001000 '
b00000000000000000000000000000000 (
#221
0#
#222
1#
b00000000 &
b00000000000000000000000000000000 '
b00000000000000000000000000000001 (
#223
0#
#224
1#
b00000001 &
b00000000000000000000000000000001 '
b00000000000000000000000000000010 (
#225
0#
#226
1#
b00000011 &
b00000000000000000000000000000010 '
b00000000000000000000000000000011 (
#227
0#
#228
1#
b00000111 &
b00000000000000000000000000000011 '
b00000000000000000000000000000100 (
#229
0#
#230
1#
b00001111 &
b00000000000000000000000000000100 '
b00000000000000000000000000000101 (
#231
0#
#232
1#
b00011111 &
b00000000000000000000000000000101 '
b00000000000000000000000000000110 (
#233
0#
#234
1#
b00111111 &
b00000000000000000000000000000110 '
b00000000000000000000000000000111 (
#235
0#
#236
1#
b01111111 &
b00000000000000000000000000000111 '
b00000000000000000000000000001000 (
#237
0#
#238
1#
b11111111 &
b00000000000000000000000000001000 '
b00000000000000000000000000000000 (
#239
0#
#240
1#
b00000000 &
b00000000000000000000000000000000 '
b00000000000000000000000000000001 (
#241
0#
#242
1#
b00000001 &
b00000000000000000000000000000001 '
b00000000000000000000000000000010 (
#243
0#
#244
1#
b00000011 &
b00000000000000000000000000000010 '
b00000000000000000000000000000011 (
#245
0#
#246
1#
b00000111 &
b00000000000000000000000000000011 '
b00000000000000000000000000000100 (
#247
0#
#248
1#
b00001111 &
b00000000000000000000000000000100 '
b00000000000000000000000000000101 (
#249
0#
#250
1#
b00011111 &
b00000000000000000000000000000101 '
b00000000000000000000000000000110 (
#251
0#
#252
1#
b00111111 &
b00000000000000000000000000000110 '
b00000000000000000000000000000111 (
#253
0#
#254
1#
b01111111 &
b00000000000000000000000000000111 '
b00000000000000000000000000001000 (
#255
0#
#256
1#
b11111111 &
b00000000000000000000000000001000 '
b00000000000000000000000000000000 (
#257
0#
#258
1#
b00000000 &
b00000000000000000000000000000000 '
b00000000000000000000000000000001 (
#259
0#
#260
1#
b00000001 &
b00000000000000000000000000000001 '
b00000000000000000000000000000010 (
#261
0#
#262
1#
b00000011 &
b00000000000000000000000000000010 '
b00000000000000000000000000000011 (
#263
0#
#264
1#
b00000111 &
b00000000000000000000000000000011 '
b00000000000000000000000000000100 (
#265
0#
#266
1#
b00001111 &
b00000000000000000000000000000100 '
b00000000000000000000000000000101 (
#267
0#
#268
1#
b00011111 &
b00000000000000000000000000000101 '
b00000000000000000000000000000110 (
#269
0#
#270
1#
b00111111 &
b00000000000000000000000000000110 '
b00000000000000000000000000000111 (
#271
0#
#272
1#
b01111111 &
b00000000000000000000000000000111 '
b00000000000000000000000000001000 (
#273
0#
#274
1#
b11111111 &
b00000000000000000000000000001000 '
b00000000000000000000000000000000 (
#275
0#
#276
1#
b00000000 &
b00000000000000000000000000000000 '
b00000000000000000000000000000001 (
#277
0#
#278
1#
b00000001 &
b00000000000000000000000000000001 '
b00000000000000000000000000000010 (
#279
0#
#280
1#
b00000011 &
b00000000000000000000000000000010 '
b00000000000000000000000000000011 (
#281
0#
#282
1#
b00000111 &
b00000000000000000000000000000011 '
b00000000000000000000000000000100 (
#283
0#
#284
1#
b00001111 &
b00000000000000000000000000000100 '
b00000000000000000000000000000101 (
#285
0#
#286
1#
b00011111 &
b00000000000000000000000000000101 '
b00000000000000000000000000000110 (
#287
0#
#288
1#
b00111111 &
b00000000000000000000000000000110 '
b00000000000000000000000000000111 (
#289
0#
#290
1#
b01111111 &
b00000000000000000000000000000111 '
b00000000000000000000000000001000 (
#291
0#
#292
1#
b11111111 &
b00000000000000000000000000001000 '
b00000000000000000000000000000000 (
#293
0#
#294
1#
b00000000 &
b00000000000000000000000000000000 '
b00000000000000000000000000000001 (
#295
0#
#296
1#
b00000001 &
b00000000000000000000000000000001 '
b00000000000000000000000000000010 (
#297
0#
#298
1#
b00000011 &
b00000000000000000000000000000010 '
b00000000000000000000000000000011 (
#299
0#
#300
1#
b00000111 &
b00000000000000000000000000000011 '
b00000000000000000000000000000100 (
#301
0#
#302
1#
b00001111 &
b00000000000000000000000000000100 '
b00000000000000000000000000000101 (
#303
0#
#304
1#
b00011111 &
b00000000000000000000000000000101 '
b00000000000000000000000000000110 (
#305
0#
#306
1#
b00111111 &
b00000000000000000000000000000110 '
b00000000000000000000000000000111 (
#307
0#
#308
1#
b01111111 &
b00000000000000000000000000000111 '
b00000000000000000000000000001000 (
#309
0#
#310
1#
b11111111 &
b00000000000000000000000000001000 '
b00000000000000000000000000000000 (
#311
0#
#312
1#
b00000000 &
b00000000000000000000000000000000 '
b00000000000000000000000000000001 (
#313
0#
#314
1#
b00000001 &
b00000000000000000000000000000001 '
b00000000000000000000000000000010 (
#315
0#
#316
1#
b00000011 &
b00000000000000000000000000000010 '
b00000000000000000000000000000011 (
#317
0#
#318
1#
b00000111 &
b00000000000000000000000000000011 '
b00000000000000000000000000000100 (
#319
0#
#320
1#
b00001111 &
b00000000000000000000000000000100 '
b00000000000000000000000000000101 (
#321
0#
#322
1#
b00011111 &
b00000000000000000000000000000101 '
b00000000000000000000000000000110 (
#323
0#
#324
1#
b00111111 &
b00000000000000000000000000000110 '
b00000000000000000000000000000111 (
#325
0#
#326
1#
b01111111 &
b00000000000000000000000000000111 '
b00000000000000000000000000001000 (
#327
0#
#328
1#
b11111111 &
b00000000000000000000000000001000 '
b00000000000000000000000000000000 (
#329
0#
#330
1#
b00000000 &
b00000000000000000000000000000000 '
b00000000000000000000000000000001 (
#331
0#
#332
1#
b00000001 &
b00000000000000000000000000000001 '
b00000000000000000000000000000010 (
#333
0#
#334
1#
b00000011 &
b00000000000000000000000000000010 '
b00000000000000000000000000000011 (
#335
0#
#336
1#
b00000111 &
b00000000000000000000000000000011 '
b00000000000000000000000000000100 (
#337
0#
#338
1#
b00001111 &
b00000000000000000000000000000100 '
b00000000000000000000000000000101 (
#339
0#
#340
1#
b00011111 &
b00000000000000000000000000000101 '
b00000000000000000000000000000110 (
#341
0#
#342
1#
b00111111 &
b00000000000000000000000000000110 '
b00000000000000000000000000000111 (
#343
0#
#344
1#
b01111111 &
b00000000000000000000000000000111 '
b00000000000000000000000000001000 (
#345
0#
#346
1#
b11111111 &
b00000000000000000000000000001000 '
b00000000000000000000000000000000 (
#347
0#
#348
1#
b00000000 &
b00000000000000000000000000000000 '
b00000000000000000000000000000001 (
#349
0#
#350
1#
b00000001 &
b00000000000000000000000000000001 '
b00000000000000000000000000000010 (
#351
0#
#352
1#
b00000011 &
b00000000000000000000000000000010 '
b00000000000000000000000000000011 (
#353
0#
#354
1#
b00000111 &
b00000000000000000000000000000011 '
b00000000000000000000000000000100 (
#355
0#
#356
1#
b00001111 &
b00000000000000000000000000000100 '
b00000000000000000000000000000101 (
#357
0#
#358
1#
b00011111 &
b00000000000000000000000000000101 '
b00000000000000000000000000000110 (
#359
0#
#360
1#
b00111111 &
b00000000000000000000000000000110 '
b00000000000000000000000000000111 (
#361
0#
#362
1#
b01111111 &
b00000000000000000000000000000111 '
b00000000000000000000000000001000 (
#363
0#
#364
1#
b11111111 &
b00000000000000000000000000001000 '
b00000000000000000000000000000000 (
#365
0#
#366
1#
b00000000 &
b00000000000000000000000000000000 '
b00000000000000000000000000000001 (
#367
0#
#368
1#
b00000001 &
b00000000000000000000000000000001 '
b00000000000000000000000000000010 (
#369
0#
#370
1#
b00000011 &
b00000000000000000000000000000010 '
b00000000000000000000000000000011 (
#371
0#
#372
1#
b00000111 &
b00000000000000000000000000000011 '
b00000000000000000000000000000100 (
#373
0#
#374
1#
b00001111 &
b00000000000000000000000000000100 '
b00000000000000000000000000000101 (
#375
0#
#376
1#
b00011111 &
b00000000000000000000000000000101 '
b00000000000000000000000000000110 (
#377
0#
#378
1#
b00111111 &
b00000000000000000000000000000110 '
b00000000000000000000000000000111 (
#379
0#
#380
1#
b01111111 &
b00000000000000000000000000000111 '
b00000000000000000000000000001000 (
#381
0#
#382
1#
b11111111 &
b00000000000000000000000000001000 '
b00000000000000000000000000000000 (
#383
0#
#384
1#
b00000000 &
b00000000000000000000000000000000 '
b00000000000000000000000000000001 (
#385
0#
#386
1#
b00000001 &
b00000000000000000000000000000001 '
b00000000000000000000000000000010 (
#387
0#
#388
1#
b00000011 &
b00000000000000000000000000000010 '
b00000000000000000000000000000011 (
#389
0#
#390
1#
b00000111 &
b00000000000000000000000000000011 '
b00000000000000000000000000000100 (
#391
0#
#392
1#
b00001111 &
b00000000000000000000000000000100 '
b00000000000000000000000000000101 (
#393
0#
#394
1#
b00011111 &
b00000000000000000000000000000101 '
b00000000000000000000000000000110 (
#395
0#
#396
1#
b00111111 &
b00000000000000000000000000000110 '
b00000000000000000000000000000111 (
#397
0#
#398
1#
b01111111 &
b00000000000000000000000000000111 '
b00000000000000000000000000001000 (
#399
0#
#400
1#
b11111111 &
b00000000000000000000000000001000 '
b00000000000000000000000000000000 (
#401
0#
#402
1#
b00000000 &
b00000000000000000000000000000000 '
b00000000000000000000000000000001 (
#403
0#
#404
1#
b00000001 &
b00000000000000000000000000000001 '
b00000000000000000000000000000010 (
#405
0#
#406
1#
b00000011 &
b00000000000000000000000000000010 '
b00000000000000000000000000000011 (
#407
0#
#408
1#
b00000111 &
b00000000000000000000000000000011 '
b00000000000000000000000000000100 (
#409
0#
#410
1#
b00001111 &
b00000000000000000000000000000100 '
b00000000000000000000000000000101 (
#411
0#
#412
1#
b00011111 &
b00000000000000000000000000000101 '
b00000000000000000000000000000110 (
#413
0#
#414
1#
b00111111 &
b00000000000000000000000000000110 '
b00000000000000000000000000000111 (
#415
0#
#416
1#
b01111111 &
b00000000000000000000000000000111 '
b00000000000000000000000000001000 (
#417
0#
#418
1#
b11111111 &
b00000000000000000000000000001000 '
b00000000000000000000000000000000 (
#419
0#
#420
1#
b00000000 &
b00000000000000000000000000000000 '
b00000000000000000000000000000001 (
#421
0#
#422
1#
b00000001 &
b00000000000000000000000000000001 '
b00000000000000000000000000000010 (
#423
0#
#424
1#
b00000011 &
b00000000000000000000000000000010 '
b00000000000000000000000000000011 (
#425
0#
#426
1#
b00000111 &
b00000000000000000000000000000011 '
b00000000000000000000000000000100 (
#427
0#
#428
1#
b00001111 &
b00000000000000000000000000000100 '
b00000000000000000000000000000101 (
#429
0#
#430
1#
b00011111 &
b00000000000000000000000000000101 '
b00000000000000000000000000000110 (
#431
0#
#432
1#
b00111111 &
b00000000000000000000000000000110 '
b00000000000000000000000000000111 (
#433
0#
#434
1#
b01111111 &
b00000000000000000000000000000111 '
b00000000000000000000000000001000 (
#435
0#
#436
1#
b11111111 &
b00000000000000000000000000001000 '
b00000000000000000000000000000000 (
#437
0#
#438
1#
b00000000 &
b00000000000000000000000000000000 '
b00000000000000000000000000000001 (
#439
0#
#440
1#
b00000001 &
b00000000000000000000000000000001 '
b00000000000000000000000000000010 (
#441
0#
#442
1#
b00000011 &
b00000000000000000000000000000010 '
b00000000000000000000000000000011 (
#443
0#
#444
1#
b00000111 &
b00000000000000000000000000000011 '
b00000000000000000000000000000100 (
#445
0#
#446
1#
b00001111 &
b00000000000000000000000000000100 '
b00000000000000000000000000000101 (
#447
0#
#448
1#
b00011111 &
b00000000000000000000000000000101 '
b00000000000000000000000000000110 (
#449
0#
#450
1#
b00111111 &
b00000000000000000000000000000110 '
b00000000000000000000000000000111 (
#451
0#
#452
1#
b01111111 &
b00000000000000000000000000000111 '
b00000000000000000000000000001000 (
#453
0#
#454
1#
b11111111 &
b00000000000000000000000000001000 '
b00000000000000000000000000000000 (
#455
0#
#456
1#
b00000000 &
b00000000000000000000000000000000 '
b00000000000000000000000000000001 (
#457
0#
#458
1#
b00000001 &
b00000000000000000000000000000001 '
b00000000000000000000000000000010 (
#459
0#
#460
1#
b00000011 &
b00000000000000000000000000000010 '
b00000000000000000000000000000011 (
#461
0#
#462
1#
b00000111 &
b00000000000000000000000000000011 '
b00000000000000000000000000000100 (
#463
0#
#464
1#
b00001111 &
b00000000000000000000000000000100 '
b00000000000000000000000000000101 (
#465
0#
#466
1#
b00011111 &
b00000000000000000000000000000101 '
b00000000000000000000000000000110 (
#467
0#
#468
1#
b00111111 &
b00000000000000000000000000000110 '
b00000000000000000000000000000111 (
#469
0#
#470
1#
b01111111 &
b00000000000000000000000000000111 '
b00000000000000000000000000001000 (
#471
0#
#472
1#
b11111111 &
b00000000000000000000000000001000 '
b00000000000000000000000000000000 (
#473
0#
#474
1#
b00000000 &
b00000000000000000000000000000000 '
b00000000000000000000000000000001 (
#475
0#
#476
1#
b00000001 &
b00000000000000000000000000000001 '
b00000000000000000000000000000010 (
#477
0#
#478
1#
b00000011 &
b00000000000000000000000000000010 '
b00000000000000000000000000000011 (
#479
0#
#480
1#
b00000111 &
b00000000000000000000000000000011 '
b00000000000000000000000000000100 (
#481
0#
#482
1#
b00001111 &
b00000000000000000000000000000100 '
b00000000000000000000000000000101 (
#483
0#
#484
1#
b00011111 &
b00000000000000000000000000000101 '
b00000000000000000000000000000110 (
#485
0#
#486
1#
b00111111 &
b00000000000000000000000000000110 '
b00000000000000000000000000000111 (
#487
0#
#488
1#
b01111111 &
b00000000000000000000000000000111 '
b00000000000000000000000000001000 (
#489
0#
#490
1#
b11111111 &
b00000000000000000000000000001000 '
b00000000000000000000000000000000 (
#491
0#
#492
1#
b00000000 &
b00000000000000000000000000000000 '
b00000000000000000000000000000001 (
#493
0#
#494
1#
b00000001 &
b00000000000000000000000000000001 '
b00000000000000000000000000000010 (
#495
0#
#496
1#
b00000011 &
b00000000000000000000000000000010 '
b00000000000000000000000000000011 (
#497
0#
#498
1#
b00000111 &
b00000000000000000000000000000011 '
b00000000000000000000000000000100 (
#499
0#
#500
1#
b00001111 &
b00000000000000000000000000000100 '
b00000000000000000000000000000101 (
#501
0#
#502
1#
b00011111 &
b00000000000000000000000000000101 '
b00000000000000000000000000000110 (
#503
0#
#504
1#
b00111111 &
b00000000000000000000000000000110 '
b00000000000000000000000000000111 (
#505
0#
#506
1#
b01111111 &
b00000000000000000000000000000111 '
b00000000000000000000000000001000 (
#507
0#
#508
1#
b11111111 &
b00000000000000000000000000001000 '
b00000000000000000000000000000000 (
#509
0#
#510
1#
b00000000 &
b00000000000000000000000000000000 '
b00000000000000000000000000000001 (
#511
0#
#512
1#
b00000001 &
b00000000000000000000000000000001 '
b00000000000000000000000000000010 (
#513
0#
#514
1#
b00000011 &
b00000000000000000000000000000010 '
b00000000000000000000000000000011 (
#515
0#
#516
1#
b00000111 &
b00000000000000000000000000000011 '
b00000000000000000000000000000100 (
#517
0#
#518
1#
b00001111 &
b00000000000000000000000000000100 '
b00000000000000000000000000000101 (
#519
0#
#520
1#
b00011111 &
b00000000000000000000000000000101 '
b00000000000000000000000000000110 (
#521
0#
#522
1#
b00111111 &
b00000000000000000000000000000110 '
b00000000000000000000000000000111 (
#523
0#
#524
1#
b01111111 &
b00000000000000000000000000000111 '
b00000000000000000000000000001000 (
#525
0#
#526
1#
b11111111 &
b00000000000000000000000000001000 '
b00000000000000000000000000000000 (
#527
0#
#528
1#
b00000000 &
b00000000000000000000000000000000 '
b00000000000000000000000000000001 (
#529
0#
#530
1#
b00000001 &
b00000000000000000000000000000001 '
b00000000000000000000000000000010 (
#531
0#
#532
1#
b00000011 &
b00000000000000000000000000000010 '
b00000000000000000000000000000011 (
#533
0#
#534
1#
b00000111 &
b00000000000000000000000000000011 '
b00000000000000000000000000000100 (
#535
0#
#536
1#
b00001111 &
b00000000000000000000000000000100 '
b00000000000000000000000000000101 (
#537
0#
#538
1#
b00011111 &
b00000000000000000000000000000101 '
b00000000000000000000000000000110 (
#539
0#
#540
1#
b00111111 &
b00000000000000000000000000000110 '
b00000000000000000000000000000111 (
#541
0#
#542
1#
b01111111 &
b00000000000000000000000000000111 '
b00000000000000000000000000001000 (
#543
0#
#544
1#
b11111111 &
b00000000000000000000000000001000 '
b00000000000000000000000000000000 (
#545
0#
#546
1#
b00000000 &
b00000000000000000000000000000000 '
b00000000000000000000000000000001 (
#547
0#
#548
1#
b00000001 &
b00000000000000000000000000000001 '
b00000000000000000000000000000010 (
#549
0#
#550
1#
b00000011 &
b00000000000000000000000000000010 '
b00000000000000000000000000000011 (
#551
0#
#552
1#
b00000111 &
b00000000000000000000000000000011 '
b00000000000000000000000000000100 (
#553
0#
#554
1#
b00001111 &
b00000000000000000000000000000100 '
b00000000000000000000000000000101 (
#555
0#
#556
1#
b00011111 &
b00000000000000000000000000000101 '
b00000000000000000000000000000110 (
#557
0#
#558
1#
b00111111 &
b00000000000000000000000000000110 '
b00000000000000000000000000000111 (
#559
0#
#560
1#
b01111111 &
b00000000000000000000000000000111 '
b00000000000000000000000000001000 (
#561
0#
#562
1#
b11111111 &
b00000000000000000000000000001000 '
b00000000000000000000000000000000 (
#563
0#
#564
1#
b00000000 &
b00000000000000000000000000000000 '
b00000000000000000000000000000001 (
#565
0#
#566
1#
b00000001 &
b00000000000000000000000000000001 '
b00000000000000000000000000000010 (
#567
0#
#568
1#
b00000011 &
b00000000000000000000000000000010 '
b00000000000000000000000000000011 (
#569
0#
#570
1#
b00000111 &
b00000000000000000000000000000011 '
b00000000000000000000000000000100 (
#571
0#
#572
1#
b00001111 &
b00000000000000000000000000000100 '
b00000000000000000000000000000101 (
#573
0#
#574
1#
b00011111 &
b00000000000000000000000000000101 '
b00000000000000000000000000000110 (
#575
0#
#576
1#
b00111111 &
b00000000000000000000000000000110 '
b00000000000000000000000000000111 (
#577
0#
#578
1#
b01111111 &
b00000000000000000000000000000111 '
b00000000000000000000000000001000 (
#579
0#
#580
1#
b11111111 &
b00000000000000000000000000001000 '
b00000000000000000000000000000000 (
#581
0#
#582
1#
b00000000 &
b00000000000000000000000000000000 '
b00000000000000000000000000000001 (
#583
0#
